core/BaseConfig.py
core/handler.py
core/httpclient.py
core/interface.py
core/reactor.py
recorder/app.py
recorder/common/accelerometer.py
recorder/common/config.py
recorder/common/heartbeater.py
recorder/common/i2c_io.py
recorder/common/mpu6050.py
recorder/common/smbus_io.py
recorder/resources/measurements.py
recorder/resources/recordingdevices.py
vibe_recorder-0.4.1.dist-info/DESCRIPTION.rst
vibe_recorder-0.4.1.dist-info/METADATA
vibe_recorder-0.4.1.dist-info/RECORD
vibe_recorder-0.4.1.dist-info/WHEEL
vibe_recorder-0.4.1.dist-info/entry_points.txt
vibe_recorder-0.4.1.dist-info/metadata.json
vibe_recorder-0.4.1.dist-info/top_level.txt
